mqtls/__init__.py
mqtls-0.5.dist-info/LICENSE.txt
mqtls-0.5.dist-info/METADATA
mqtls-0.5.dist-info/WHEEL
mqtls-0.5.dist-info/top_level.txt
mqtls-0.5.dist-info/RECORD
