Metadata-Version: 2.1
Name: mqtls
Version: 0.5
Summary: MqTLS client for python
Home-page: https://github.com/efrenbg1/mqtls-python
Author: Efrén Boyarizo
Author-email: efren@boyarizo.es
License: wtfpl
Download-URL: https://github.com/efrenbg1/mqtls-python/archive/0.5.tar.gz
Keywords: MqTLS,gobroker,client
Platform: UNKNOWN
Classifier: Development Status :: 3 - Alpha
Classifier: Intended Audience :: Developers
Classifier: Topic :: Software Development :: Build Tools
